cht/__init__.py
cht/bathymetry/__init__.py
cht/bathymetry/bathymetry_database.py
cht/bathymetry/tiling.py
cht/bathymetry/tiling_example.py
cht/bathymetry/tiling_example_gebco22.py
cht/bathymetry/utils.py
cht/beware/__init__.py
cht/beware/beware.py
cht/delft3dfm/__init__.py
cht/delft3dfm/delft3dfm.py
cht/hurrywave/__init__.py
cht/hurrywave/bathymetry.py
cht/hurrywave/boundary_conditions.py
cht/hurrywave/grid.py
cht/hurrywave/hurrywave.py
cht/hurrywave/hurrywave_builder.py
cht/hurrywave/hurrywave_domain.py
cht/hurrywave/input.py
cht/hurrywave/mask.py
cht/hurrywave/observation_points.py
cht/hurrywave/to_xugrid.py
cht/meteo/__init__.py
cht/meteo/coamps_analysis.py
cht/meteo/coamps_tc_forecast.py
cht/meteo/coamps_tc_hindcast.py
cht/meteo/coamps_tc_ufl_d01.py
cht/meteo/gfs_anl_0p50.py
cht/meteo/gfs_anl_0p50_02.py
cht/meteo/gfs_anl_0p50_03.py
cht/meteo/gfs_anl_0p50_04.py
cht/meteo/gfs_forecast_0p25.py
cht/meteo/gfs_forecast_0p25_02.py
cht/meteo/meteo.py
cht/meteo/test_coamps.py
cht/misc/__init__.py
cht/misc/deltares_ini.py
cht/misc/fileops.py
cht/misc/geometry.py
cht/misc/misc_tools.py
cht/misc/pli_file.py
cht/misc/prob_maps.py
cht/misc/sftp.py
cht/misc/tekal.py
cht/misc/xmlkit.py
cht/model_builder/model_builder.py
cht/nesting/__init__.py
cht/nesting/nest1.py
cht/nesting/nest2.py
cht/nesting/nesting.py
cht/observation_stations/__init__.py
cht/observation_stations/_ndbc.py
cht/observation_stations/_noaa_coops.py
cht/observation_stations/observation_stations.py
cht/physics/__init__.py
cht/physics/deshoal.py
cht/physics/disper.py
cht/physics/vo21.py
cht/sfincs/__init__.py
cht/sfincs/quadtree.py
cht/sfincs/regulargrid.py
cht/sfincs/sfincs.py
cht/sfincs/sfincs_builder.py
cht/sfincs/subgrid.py
cht/sfincs2/__init__.py
cht/sfincs2/boundary_conditions.py
cht/sfincs2/grid.py
cht/sfincs2/input.py
cht/sfincs2/mask.py
cht/sfincs2/observation_points.py
cht/sfincs2/quadtree_grid.py
cht/sfincs2/quadtree_grid_snapwave.py
cht/sfincs2/regular_grid.py
cht/sfincs2/sfincs.py
coastalhazardstoolkit-0.2.0.dist-info/LICENSE
coastalhazardstoolkit-0.2.0.dist-info/METADATA
coastalhazardstoolkit-0.2.0.dist-info/WHEEL
coastalhazardstoolkit-0.2.0.dist-info/top_level.txt
coastalhazardstoolkit-0.2.0.dist-info/RECORD
