Metadata-Version: 2.1
Name: coastalhazardstoolkit
Version: 0.2.0
Author-email: Maarten van Ormondt <maarten.vanormondt@deltares-usa.us>, Roel de Goede <roel.degoede@deltares.nl>, Kees Nederhoff <kees.nederhoff@deltares-usa.us>, Tim Leijnse <tim.leijnse@deltares.nl>, Panos Athanasiou <panos.athanasiou@deltares.nl>
Requires-Python: >=3.10
License-File: LICENSE
Requires-Dist: geopandas (>=0.8)
Requires-Dist: numpy
Requires-Dist: pandas
Requires-Dist: pyproj
Requires-Dist: rasterio
Requires-Dist: shapely
Requires-Dist: scipy
Requires-Dist: xarray
Requires-Dist: wget
Requires-Dist: elementpath
Requires-Dist: geojson
Requires-Dist: Pillow
Requires-Dist: matplotlib
Requires-Dist: noaa-coops
Requires-Dist: metpy
Requires-Dist: siphon
Requires-Dist: netCDF4
Requires-Dist: mat73
Requires-Dist: tabulate
Requires-Dist: pyyaml
Requires-Dist: toml
